pollination/lbt_honeybee/__init__.py
pollination/lbt_honeybee/edit.py
pollination/lbt_honeybee/postprocess.py
pollination_lbt_honeybee-0.1.17.dist-info/LICENSE
pollination_lbt_honeybee-0.1.17.dist-info/METADATA
pollination_lbt_honeybee-0.1.17.dist-info/WHEEL
pollination_lbt_honeybee-0.1.17.dist-info/top_level.txt
pollination_lbt_honeybee-0.1.17.dist-info/RECORD
